{
  "playerData": [
      {
          "emailHash": "a2811d3d58497b8f53fa443a3fccde32",
          "name": "jim"
      }
  ],
  "matchData": {
    "settings": {
      "players": {
        "names": ["player0"],
        "count": 1
      }
    },
    "score": 0,
    "fraudTypes": [{
      "type": 0
    }, {
      "type": 1
    }, {
      "type": 2
    }, {
      "type": 3
    }, {
      "type": 4
    }, {
      "type": 5
    }],
    "winner": null,
    "checkpoints": [{
      "description": "Rejects odd transactions",
      "falsePositives": 38,
      "id": 0,
      "frauds": [{
        "detectedFrauds": 3,
        "type": 1
      }, {
        "detectedFrauds": 2,
        "type": 2
      }, {
        "detectedFrauds": 3,
        "type": 3
      }, {
        "detectedFrauds": 2,
        "type": 4
      }, {
        "detectedFrauds": 2,
        "type": 5
      }]
    }, {
      "description": "Rejects transaction amounts higher than 100.00",
      "falsePositives": 12,
      "id": 1,
      "frauds": [{
        "detectedFrauds": 4,
        "type": 1
      }, {
        "detectedFrauds": 0,
        "type": 2
      }, {
        "detectedFrauds": 1,
        "type": 3
      }, {
        "detectedFrauds": 0,
        "type": 4
      }, {
        "detectedFrauds": 0,
        "type": 5
      }]
    }],
    "states": [{
      "isFraudulent": false,
      "exception": null,
      "blockingCheckPointIds": [0],
      "isRefused": true,
      "round": 1
    }, {
      "isFraudulent": false,
      "exception": null,
      "blockingCheckPointIds": [1],
      "isRefused": true,
      "round": 2
    }, {
      "isFraudulent": false,
      "exception": null,
      "blockingCheckPointIds": [0],
      "isRefused": true,
      "round": 3
    }, {
      "isFraudulent": false,
      "exception": null,
      "blockingCheckPointIds": [],
      "isRefused": false,
      "round": 4
    }, {
      "isFraudulent": true,
      "exception": null,
      "blockingCheckPointIds": [0],
      "isRefused": true,
      "round": 5
    }, {
      "isFraudulent": false,
      "exception": null,
      "blockingCheckPointIds": [],
      "isRefused": false,
      "round": 6
    }, {
      "isFraudulent": false,
      "exception": null,
      "blockingCheckPointIds": [0],
      "isRefused": true,
      "round": 7
    }, {
      "isFraudulent": false,
      "exception": null,
      "blockingCheckPointIds": [],
      "isRefused": false,
      "round": 8
    }, {
      "isFraudulent": false,
      "exception": null,
      "blockingCheckPointIds": [0],
      "isRefused": true,
      "round": 9
    }, {
      "isFraudulent": false,
      "exception": null,
      "blockingCheckPointIds": [],
      "isRefused": false,
      "round": 10
    }, {
      "isFraudulent": false,
      "exception": null,
      "blockingCheckPointIds": [0],
      "isRefused": true,
      "round": 11
    }, {
      "isFraudulent": false,
      "exception": null,
      "blockingCheckPointIds": [],
      "isRefused": false,
      "round": 12
    }, {
      "isFraudulent": false,
      "exception": null,
      "blockingCheckPointIds": [0],
      "isRefused": true,
      "round": 13
    }, {
      "isFraudulent": true,
      "exception": null,
      "blockingCheckPointIds": [1],
      "isRefused": true,
      "round": 14
    }, {
      "isFraudulent": false,
      "exception": null,
      "blockingCheckPointIds": [0],
      "isRefused": true,
      "round": 15
    }, {
      "isFraudulent": false,
      "exception": null,
      "blockingCheckPointIds": [],
      "isRefused": false,
      "round": 16
    }, {
      "isFraudulent": true,
      "exception": null,
      "blockingCheckPointIds": [0],
      "isRefused": true,
      "round": 17
    }, {
      "isFraudulent": false,
      "exception": null,
      "blockingCheckPointIds": [],
      "isRefused": false,
      "round": 18
    }, {
      "isFraudulent": false,
      "exception": null,
      "blockingCheckPointIds": [0],
      "isRefused": true,
      "round": 19
    }, {
      "isFraudulent": false,
      "exception": null,
      "blockingCheckPointIds": [],
      "isRefused": false,
      "round": 20
    }, {
      "isFraudulent": false,
      "exception": null,
      "blockingCheckPointIds": [0],
      "isRefused": true,
      "round": 21
    }, {
      "isFraudulent": false,
      "exception": null,
      "blockingCheckPointIds": [],
      "isRefused": false,
      "round": 22
    }, {
      "isFraudulent": true,
      "exception": null,
      "blockingCheckPointIds": [0],
      "isRefused": true,
      "round": 23
    }, {
      "isFraudulent": false,
      "exception": null,
      "blockingCheckPointIds": [],
      "isRefused": false,
      "round": 24
    }, {
      "isFraudulent": false,
      "exception": null,
      "blockingCheckPointIds": [0],
      "isRefused": true,
      "round": 25
    }, {
      "isFraudulent": false,
      "exception": null,
      "blockingCheckPointIds": [],
      "isRefused": false,
      "round": 26
    }, {
      "isFraudulent": false,
      "exception": null,
      "blockingCheckPointIds": [0],
      "isRefused": true,
      "round": 27
    }, {
      "isFraudulent": false,
      "exception": null,
      "blockingCheckPointIds": [],
      "isRefused": false,
      "round": 28
    }, {
      "isFraudulent": false,
      "exception": null,
      "blockingCheckPointIds": [0],
      "isRefused": true,
      "round": 29
    }, {
      "isFraudulent": false,
      "exception": null,
      "blockingCheckPointIds": [1],
      "isRefused": true,
      "round": 30
    }, {
      "isFraudulent": false,
      "exception": null,
      "blockingCheckPointIds": [0],
      "isRefused": true,
      "round": 31
    }, {
      "isFraudulent": true,
      "exception": null,
      "blockingCheckPointIds": [1],
      "isRefused": true,
      "round": 32
    }, {
      "isFraudulent": false,
      "exception": null,
      "blockingCheckPointIds": [0, 1],
      "isRefused": true,
      "round": 33
    }, {
      "isFraudulent": false,
      "exception": null,
      "blockingCheckPointIds": [],
      "isRefused": false,
      "round": 34
    }, {
      "isFraudulent": false,
      "exception": null,
      "blockingCheckPointIds": [0],
      "isRefused": true,
      "round": 35
    }, {
      "isFraudulent": false,
      "exception": null,
      "blockingCheckPointIds": [],
      "isRefused": false,
      "round": 36
    }, {
      "isFraudulent": false,
      "exception": null,
      "blockingCheckPointIds": [0, 1],
      "isRefused": true,
      "round": 37
    }, {
      "isFraudulent": false,
      "exception": null,
      "blockingCheckPointIds": [],
      "isRefused": false,
      "round": 38
    }, {
      "isFraudulent": false,
      "exception": null,
      "blockingCheckPointIds": [0],
      "isRefused": true,
      "round": 39
    }, {
      "isFraudulent": false,
      "exception": null,
      "blockingCheckPointIds": [],
      "isRefused": false,
      "round": 40
    }, {
      "isFraudulent": false,
      "exception": null,
      "blockingCheckPointIds": [0],
      "isRefused": true,
      "round": 41
    }, {
      "isFraudulent": true,
      "exception": null,
      "blockingCheckPointIds": [],
      "isRefused": false,
      "round": 42
    }, {
      "isFraudulent": false,
      "exception": null,
      "blockingCheckPointIds": [0],
      "isRefused": true,
      "round": 43
    }, {
      "isFraudulent": false,
      "exception": null,
      "blockingCheckPointIds": [1],
      "isRefused": true,
      "round": 44
    }, {
      "isFraudulent": false,
      "exception": null,
      "blockingCheckPointIds": [0, 1],
      "isRefused": true,
      "round": 45
    }, {
      "isFraudulent": false,
      "exception": null,
      "blockingCheckPointIds": [],
      "isRefused": false,
      "round": 46
    }, {
      "isFraudulent": false,
      "exception": null,
      "blockingCheckPointIds": [0],
      "isRefused": true,
      "round": 47
    }, {
      "isFraudulent": false,
      "exception": null,
      "blockingCheckPointIds": [],
      "isRefused": false,
      "round": 48
    }, {
      "isFraudulent": true,
      "exception": null,
      "blockingCheckPointIds": [0],
      "isRefused": true,
      "round": 49
    }, {
      "isFraudulent": false,
      "exception": null,
      "blockingCheckPointIds": [],
      "isRefused": false,
      "round": 50
    }, {
      "isFraudulent": true,
      "exception": null,
      "blockingCheckPointIds": [0],
      "isRefused": true,
      "round": 51
    }, {
      "isFraudulent": true,
      "exception": null,
      "blockingCheckPointIds": [],
      "isRefused": false,
      "round": 52
    }, {
      "isFraudulent": true,
      "exception": null,
      "blockingCheckPointIds": [0, 1],
      "isRefused": true,
      "round": 53
    }, {
      "isFraudulent": true,
      "exception": null,
      "blockingCheckPointIds": [],
      "isRefused": false,
      "round": 54
    }, {
      "isFraudulent": true,
      "exception": null,
      "blockingCheckPointIds": [0],
      "isRefused": true,
      "round": 55
    }, {
      "isFraudulent": false,
      "exception": null,
      "blockingCheckPointIds": [1],
      "isRefused": true,
      "round": 56
    }, {
      "isFraudulent": true,
      "exception": null,
      "blockingCheckPointIds": [0],
      "isRefused": true,
      "round": 57
    }, {
      "isFraudulent": false,
      "exception": null,
      "blockingCheckPointIds": [],
      "isRefused": false,
      "round": 58
    }, {
      "isFraudulent": true,
      "exception": null,
      "blockingCheckPointIds": [0],
      "isRefused": true,
      "round": 59
    }, {
      "isFraudulent": true,
      "exception": null,
      "blockingCheckPointIds": [],
      "isRefused": false,
      "round": 60
    }, {
      "isFraudulent": false,
      "exception": null,
      "blockingCheckPointIds": [0],
      "isRefused": true,
      "round": 61
    }, {
      "isFraudulent": false,
      "exception": null,
      "blockingCheckPointIds": [],
      "isRefused": false,
      "round": 62
    }, {
      "isFraudulent": false,
      "exception": null,
      "blockingCheckPointIds": [0],
      "isRefused": true,
      "round": 63
    }, {
      "isFraudulent": true,
      "exception": null,
      "blockingCheckPointIds": [],
      "isRefused": false,
      "round": 64
    }, {
      "isFraudulent": true,
      "exception": null,
      "blockingCheckPointIds": [0],
      "isRefused": true,
      "round": 65
    }, {
      "isFraudulent": false,
      "exception": null,
      "blockingCheckPointIds": [],
      "isRefused": false,
      "round": 66
    }, {
      "isFraudulent": false,
      "exception": null,
      "blockingCheckPointIds": [0],
      "isRefused": true,
      "round": 67
    }, {
      "isFraudulent": false,
      "exception": null,
      "blockingCheckPointIds": [],
      "isRefused": false,
      "round": 68
    }, {
      "isFraudulent": true,
      "exception": null,
      "blockingCheckPointIds": [0, 1],
      "isRefused": true,
      "round": 69
    }, {
      "isFraudulent": false,
      "exception": null,
      "blockingCheckPointIds": [1],
      "isRefused": true,
      "round": 70
    }, {
      "isFraudulent": false,
      "exception": null,
      "blockingCheckPointIds": [0, 1],
      "isRefused": true,
      "round": 71
    }, {
      "isFraudulent": false,
      "exception": null,
      "blockingCheckPointIds": [],
      "isRefused": false,
      "round": 72
    }, {
      "isFraudulent": false,
      "exception": null,
      "blockingCheckPointIds": [0],
      "isRefused": true,
      "round": 73
    }, {
      "isFraudulent": false,
      "exception": null,
      "blockingCheckPointIds": [],
      "isRefused": false,
      "round": 74
    }, {
      "isFraudulent": false,
      "exception": null,
      "blockingCheckPointIds": [0, 1],
      "isRefused": true,
      "round": 75
    }, {
      "isFraudulent": true,
      "exception": null,
      "blockingCheckPointIds": [1],
      "isRefused": true,
      "round": 76
    }, {
      "isFraudulent": false,
      "exception": null,
      "blockingCheckPointIds": [0],
      "isRefused": true,
      "round": 77
    }, {
      "isFraudulent": false,
      "exception": null,
      "blockingCheckPointIds": [],
      "isRefused": false,
      "round": 78
    }, {
      "isFraudulent": false,
      "exception": null,
      "blockingCheckPointIds": [0],
      "isRefused": true,
      "round": 79
    }, {
      "isFraudulent": false,
      "exception": null,
      "blockingCheckPointIds": [],
      "isRefused": false,
      "round": 80
    }, {
      "isFraudulent": false,
      "exception": null,
      "blockingCheckPointIds": [0],
      "isRefused": true,
      "round": 81
    }, {
      "isFraudulent": false,
      "exception": null,
      "blockingCheckPointIds": [],
      "isRefused": false,
      "round": 82
    }, {
      "isFraudulent": false,
      "exception": null,
      "blockingCheckPointIds": [0],
      "isRefused": true,
      "round": 83
    }, {
      "isFraudulent": false,
      "exception": null,
      "blockingCheckPointIds": [],
      "isRefused": false,
      "round": 84
    }, {
      "isFraudulent": false,
      "exception": null,
      "blockingCheckPointIds": [0],
      "isRefused": true,
      "round": 85
    }, {
      "isFraudulent": false,
      "exception": null,
      "blockingCheckPointIds": [],
      "isRefused": false,
      "round": 86
    }, {
      "isFraudulent": true,
      "exception": null,
      "blockingCheckPointIds": [0],
      "isRefused": true,
      "round": 87
    }, {
      "isFraudulent": false,
      "exception": null,
      "blockingCheckPointIds": [1],
      "isRefused": true,
      "round": 88
    }, {
      "isFraudulent": false,
      "exception": null,
      "blockingCheckPointIds": [0],
      "isRefused": true,
      "round": 89
    }, {
      "isFraudulent": false,
      "exception": null,
      "blockingCheckPointIds": [1],
      "isRefused": true,
      "round": 90
    }, {
      "isFraudulent": false,
      "exception": null,
      "blockingCheckPointIds": [0],
      "isRefused": true,
      "round": 91
    }, {
      "isFraudulent": false,
      "exception": null,
      "blockingCheckPointIds": [],
      "isRefused": false,
      "round": 92
    }, {
      "isFraudulent": false,
      "exception": null,
      "blockingCheckPointIds": [0],
      "isRefused": true,
      "round": 93
    }, {
      "isFraudulent": false,
      "exception": null,
      "blockingCheckPointIds": [],
      "isRefused": false,
      "round": 94
    }, {
      "isFraudulent": false,
      "exception": null,
      "blockingCheckPointIds": [0],
      "isRefused": true,
      "round": 95
    }, {
      "isFraudulent": false,
      "exception": null,
      "blockingCheckPointIds": [],
      "isRefused": false,
      "round": 96
    }, {
      "isFraudulent": false,
      "exception": null,
      "blockingCheckPointIds": [0],
      "isRefused": true,
      "round": 97
    }, {
      "isFraudulent": false,
      "exception": null,
      "blockingCheckPointIds": [],
      "isRefused": false,
      "round": 98
    }, {
      "isFraudulent": false,
      "exception": null,
      "blockingCheckPointIds": [0],
      "isRefused": true,
      "round": 99
    }, {
      "isFraudulent": false,
      "exception": null,
      "blockingCheckPointIds": [],
      "isRefused": false,
      "round": 100
    }]
  }
}